LICENSE
whdtscraper/__init__.py
whdtscraper/whdtscraper.py
whdtscraper-1.0.3.dist-info/LICENSE
whdtscraper-1.0.3.dist-info/WHEEL
whdtscraper-1.0.3.dist-info/METADATA
whdtscraper-1.0.3.dist-info/RECORD
